{
    "perfect[0.0]": {
        "0": {
            "cf-dcg": {
                "10000": 1e-01,
                "20000": 1e-01,
                "30000": 1e-01,
                "40000": 1e-01,
                "50000": 1e-01,
                "60000": 1e-01,
                "70000": 1e-01,
                "80000": 1e-01,
                "90000": 1e-01,
                "100000": 1e-01,
                "150000": 1e-01,
                "200000": 1e-01,
                "250000": 1e-01,
                "300000": 1e-01,
                "350000": 1e-01,
                "400000": 1e-01,
                "450000": 1e-01,
                "500000": 1e-01,
                "550000": 1e-01,
                "600000": 1e-01,
                "650000": 1e-01,
                "700000": 1e-01,
                "750000": 1e-01,
                "800000": 1e-01,
                "850000": 1e-01,
                "900000": 1e-01,
                "950000": 1e-01,
                "1000000": 1e-01
            },
            "cf-hinge": {
                "10000": 1e-01,
                "20000": 1e-01,
                "30000": 1e-01,
                "40000": 1e-01,
                "50000": 1e-01,
                "60000": 1e-01,
                "70000": 1e-01,
                "80000": 1e-01,
                "90000": 1e-01,
                "100000": 1e-01,
                "150000": 1e-01,
                "200000": 1e-01,
                "250000": 1e-01,
                "300000": 1e-01,
                "350000": 1e-01,
                "400000": 1e-01,
                "450000": 1e-01,
                "500000": 1e-01,
                "550000": 1e-01,
                "600000": 1e-01,
                "650000": 1e-01,
                "700000": 1e-01,
                "750000": 1e-01,
                "800000": 1e-01,
                "850000": 1e-01,
                "900000": 1e-01,
                "950000": 1e-01,
                "1000000": 1e-01
            },
            "hybrid-dcg": {
                "10000": 1e-01,
                "20000": 1e-01,
                "30000": 1e-01,
                "40000": 1e-01,
                "50000": 1e-01,
                "60000": 1e-01,
                "70000": 1e-01,
                "80000": 1e-01,
                "90000": 1e-01,
                "100000": 1e-01,
                "150000": 1e-01,
                "200000": 1e-01,
                "250000": 1e-01,
                "300000": 1e-01,
                "350000": 1e-01,
                "400000": 1e-01,
                "450000": 1e-01,
                "500000": 1e-01,
                "550000": 1e-01,
                "600000": 1e-01,
                "650000": 1e-01,
                "700000": 1e-01,
                "750000": 1e-01,
                "800000": 1e-01,
                "850000": 1e-01,
                "900000": 1e-01,
                "950000": 1e-01,
                "1000000": 1e-01
            },
            "hybrid-hinge": {
                "10000": 1e-01,
                "20000": 1e-01,
                "30000": 1e-01,
                "40000": 1e-01,
                "50000": 1e-01,
                "60000": 1e-01,
                "70000": 1e-01,
                "80000": 1e-01,
                "90000": 1e-01,
                "100000": 1e-01,
                "150000": 1e-01,
                "200000": 1e-01,
                "250000": 1e-01,
                "300000": 1e-01,
                "350000": 1e-01,
                "400000": 1e-01,
                "450000": 1e-01,
                "500000": 1e-01,
                "550000": 1e-01,
                "600000": 1e-01,
                "650000": 1e-01,
                "700000": 1e-01,
                "750000": 1e-01,
                "800000": 1e-01,
                "850000": 1e-01,
                "900000": 1e-01,
                "950000": 1e-01,
                "1000000": 1e-01
            }
        },
        "10": {
            "cf-dcg": {
                "10000": 1e-01,
                "20000": 1e-01,
                "30000": 1e-01,
                "40000": 1e-01,
                "50000": 1e-01,
                "60000": 1e-01,
                "70000": 1e-01,
                "80000": 1e-01,
                "90000": 1e-01,
                "100000": 1e-01,
                "150000": 1e-01,
                "200000": 1e-01,
                "250000": 1e-01,
                "300000": 1e-01,
                "350000": 1e-01,
                "400000": 1e-01,
                "450000": 1e-01,
                "500000": 1e-01,
                "550000": 1e-01,
                "600000": 1e-01,
                "650000": 1e-01,
                "700000": 1e-01,
                "750000": 1e-01,
                "800000": 1e-01,
                "850000": 1e-01,
                "900000": 1e-01,
                "950000": 1e-01,
                "1000000": 1e-01
            },
            "cf-hinge": {
                "10000": 1e-01,
                "20000": 1e-01,
                "30000": 1e-01,
                "40000": 1e-01,
                "50000": 1e-01,
                "60000": 1e-01,
                "70000": 1e-01,
                "80000": 1e-01,
                "90000": 1e-01,
                "100000": 1e-01,
                "150000": 1e-01,
                "200000": 1e-01,
                "250000": 1e-01,
                "300000": 1e-01,
                "350000": 1e-01,
                "400000": 1e-01,
                "450000": 1e-01,
                "500000": 1e-01,
                "550000": 1e-01,
                "600000": 1e-01,
                "650000": 1e-01,
                "700000": 1e-01,
                "750000": 1e-01,
                "800000": 1e-01,
                "850000": 1e-01,
                "900000": 1e-01,
                "950000": 1e-01,
                "1000000": 1e-01
            },
            "hybrid-dcg": {
                "10000": 1e-01,
                "20000": 1e-01,
                "30000": 1e-01,
                "40000": 1e-01,
                "50000": 1e-01,
                "60000": 1e-01,
                "70000": 1e-01,
                "80000": 1e-01,
                "90000": 1e-01,
                "100000": 1e-01,
                "150000": 1e-01,
                "200000": 1e-01,
                "250000": 1e-01,
                "300000": 1e-01,
                "350000": 1e-01,
                "400000": 1e-01,
                "450000": 1e-01,
                "500000": 1e-01,
                "550000": 1e-01,
                "600000": 1e-01,
                "650000": 1e-01,
                "700000": 1e-01,
                "750000": 1e-01,
                "800000": 1e-01,
                "850000": 1e-01,
                "900000": 1e-01,
                "950000": 1e-01,
                "1000000": 1e-01
            },
            "hybrid-hinge": {
                "10000": 1e-01,
                "20000": 1e-01,
                "30000": 1e-01,
                "40000": 1e-01,
                "50000": 1e-01,
                "60000": 1e-01,
                "70000": 1e-01,
                "80000": 1e-01,
                "90000": 1e-01,
                "100000": 1e-01,
                "150000": 1e-01,
                "200000": 1e-01,
                "250000": 1e-01,
                "300000": 1e-01,
                "350000": 1e-01,
                "400000": 1e-01,
                "450000": 1e-01,
                "500000": 1e-01,
                "550000": 1e-01,
                "600000": 1e-01,
                "650000": 1e-01,
                "700000": 1e-01,
                "750000": 1e-01,
                "800000": 1e-01,
                "850000": 1e-01,
                "900000": 1e-01,
                "950000": 1e-01,
                "1000000": 1e-01
            }
        }
    },
    "position[1.0]": {
        "0": {
            "cf-dcg": {
                "10000": 1e-01,
                "20000": 1e-01,
                "30000": 1e-01,
                "40000": 1e-01,
                "50000": 1e-01,
                "60000": 1e-01,
                "70000": 1e-01,
                "80000": 1e-01,
                "90000": 1e-01,
                "100000": 1e-01,
                "150000": 1e-01,
                "200000": 1e-01,
                "250000": 1e-01,
                "300000": 1e-01,
                "350000": 1e-01,
                "400000": 1e-01,
                "450000": 1e-01,
                "500000": 1e-01,
                "550000": 1e-01,
                "600000": 1e-01,
                "650000": 1e-01,
                "700000": 1e-01,
                "750000": 1e-01,
                "800000": 1e-01,
                "850000": 1e-01,
                "900000": 1e-01,
                "950000": 1e-01,
                "1000000": 1e-01
            },
            "cf-hinge": {
                "10000": 1e-01,
                "20000": 1e-01,
                "30000": 1e-01,
                "40000": 1e-01,
                "50000": 1e-01,
                "60000": 1e-01,
                "70000": 1e-01,
                "80000": 1e-01,
                "90000": 1e-01,
                "100000": 1e-01,
                "150000": 1e-01,
                "200000": 1e-01,
                "250000": 1e-01,
                "300000": 1e-01,
                "350000": 1e-01,
                "400000": 1e-01,
                "450000": 1e-01,
                "500000": 1e-01,
                "550000": 1e-01,
                "600000": 1e-01,
                "650000": 1e-01,
                "700000": 1e-01,
                "750000": 1e-01,
                "800000": 1e-01,
                "850000": 1e-01,
                "900000": 1e-01,
                "950000": 1e-01,
                "1000000": 1e-01
            },
            "hybrid-dcg": {
                "10000": 1e-01,
                "20000": 1e-01,
                "30000": 1e-01,
                "40000": 1e-01,
                "50000": 1e-01,
                "60000": 1e-01,
                "70000": 1e-01,
                "80000": 1e-01,
                "90000": 1e-01,
                "100000": 1e-01,
                "150000": 1e-01,
                "200000": 1e-01,
                "250000": 1e-01,
                "300000": 1e-01,
                "350000": 1e-01,
                "400000": 1e-01,
                "450000": 1e-01,
                "500000": 1e-01,
                "550000": 1e-01,
                "600000": 1e-01,
                "650000": 1e-01,
                "700000": 1e-01,
                "750000": 1e-01,
                "800000": 1e-01,
                "850000": 1e-01,
                "900000": 1e-01,
                "950000": 1e-01,
                "1000000": 1e-01
            },
            "hybrid-hinge": {
                "10000": 1e-01,
                "20000": 1e-01,
                "30000": 1e-01,
                "40000": 1e-01,
                "50000": 1e-01,
                "60000": 1e-01,
                "70000": 1e-01,
                "80000": 1e-01,
                "90000": 1e-01,
                "100000": 1e-01,
                "150000": 1e-01,
                "200000": 1e-01,
                "250000": 1e-01,
                "300000": 1e-01,
                "350000": 1e-01,
                "400000": 1e-01,
                "450000": 1e-01,
                "500000": 1e-01,
                "550000": 1e-01,
                "600000": 1e-01,
                "650000": 1e-01,
                "700000": 1e-01,
                "750000": 1e-01,
                "800000": 1e-01,
                "850000": 1e-01,
                "900000": 1e-01,
                "950000": 1e-01,
                "1000000": 1e-01
            }
        },
        "10": {
            "cf-dcg": {
                "10000": 1e-01,
                "20000": 1e-01,
                "30000": 1e-01,
                "40000": 1e-01,
                "50000": 1e-01,
                "60000": 1e-01,
                "70000": 1e-01,
                "80000": 1e-01,
                "90000": 1e-01,
                "100000": 1e-01,
                "150000": 1e-01,
                "200000": 1e-01,
                "250000": 1e-01,
                "300000": 1e-01,
                "350000": 1e-01,
                "400000": 1e-01,
                "450000": 1e-01,
                "500000": 1e-01,
                "550000": 1e-01,
                "600000": 1e-01,
                "650000": 1e-01,
                "700000": 1e-01,
                "750000": 1e-01,
                "800000": 1e-01,
                "850000": 1e-01,
                "900000": 1e-01,
                "950000": 1e-01,
                "1000000": 1e-01
            },
            "cf-hinge": {
                "10000": 1e-01,
                "20000": 1e-01,
                "30000": 1e-01,
                "40000": 1e-01,
                "50000": 1e-01,
                "60000": 1e-01,
                "70000": 1e-01,
                "80000": 1e-01,
                "90000": 1e-01,
                "100000": 1e-01,
                "150000": 1e-01,
                "200000": 1e-01,
                "250000": 1e-01,
                "300000": 1e-01,
                "350000": 1e-01,
                "400000": 1e-01,
                "450000": 1e-01,
                "500000": 1e-01,
                "550000": 1e-01,
                "600000": 1e-01,
                "650000": 1e-01,
                "700000": 1e-01,
                "750000": 1e-01,
                "800000": 1e-01,
                "850000": 1e-01,
                "900000": 1e-01,
                "950000": 1e-01,
                "1000000": 1e-01
            },
            "hybrid-dcg": {
                "10000": 1e-01,
                "20000": 1e-01,
                "30000": 1e-01,
                "40000": 1e-01,
                "50000": 1e-01,
                "60000": 1e-01,
                "70000": 1e-01,
                "80000": 1e-01,
                "90000": 1e-01,
                "100000": 1e-01,
                "150000": 1e-01,
                "200000": 1e-01,
                "250000": 1e-01,
                "300000": 1e-01,
                "350000": 1e-01,
                "400000": 1e-01,
                "450000": 1e-01,
                "500000": 1e-01,
                "550000": 1e-01,
                "600000": 1e-01,
                "650000": 1e-01,
                "700000": 1e-01,
                "750000": 1e-01,
                "800000": 1e-01,
                "850000": 1e-01,
                "900000": 1e-01,
                "950000": 1e-01,
                "1000000": 1e-01
            },
            "hybrid-hinge": {
                "10000": 1e-01,
                "20000": 1e-01,
                "30000": 1e-01,
                "40000": 1e-01,
                "50000": 1e-01,
                "60000": 1e-01,
                "70000": 1e-01,
                "80000": 1e-01,
                "90000": 1e-01,
                "100000": 1e-01,
                "150000": 1e-01,
                "200000": 1e-01,
                "250000": 1e-01,
                "300000": 1e-01,
                "350000": 1e-01,
                "400000": 1e-01,
                "450000": 1e-01,
                "500000": 1e-01,
                "550000": 1e-01,
                "600000": 1e-01,
                "650000": 1e-01,
                "700000": 1e-01,
                "750000": 1e-01,
                "800000": 1e-01,
                "850000": 1e-01,
                "900000": 1e-01,
                "950000": 1e-01,
                "1000000": 1e-01
            }
        }
    },
    "position[2.0]": {
        "0": {
            "cf-dcg": {
                "10000": 1e-01,
                "20000": 1e-01,
                "30000": 1e-01,
                "40000": 1e-01,
                "50000": 1e-01,
                "60000": 1e-01,
                "70000": 1e-01,
                "80000": 1e-01,
                "90000": 1e-01,
                "100000": 1e-01,
                "150000": 1e-01,
                "200000": 1e-01,
                "250000": 1e-01,
                "300000": 1e-01,
                "350000": 1e-01,
                "400000": 1e-01,
                "450000": 1e-01,
                "500000": 1e-01,
                "550000": 1e-01,
                "600000": 1e-01,
                "650000": 1e-01,
                "700000": 1e-01,
                "750000": 1e-01,
                "800000": 1e-01,
                "850000": 1e-01,
                "900000": 1e-01,
                "950000": 1e-01,
                "1000000": 1e-01
            },
            "cf-hinge": {
                "10000": 1e-01,
                "20000": 1e-01,
                "30000": 1e-01,
                "40000": 1e-01,
                "50000": 1e-01,
                "60000": 1e-01,
                "70000": 1e-01,
                "80000": 1e-01,
                "90000": 1e-01,
                "100000": 1e-01,
                "150000": 1e-01,
                "200000": 1e-01,
                "250000": 1e-01,
                "300000": 1e-01,
                "350000": 1e-01,
                "400000": 1e-01,
                "450000": 1e-01,
                "500000": 1e-01,
                "550000": 1e-01,
                "600000": 1e-01,
                "650000": 1e-01,
                "700000": 1e-01,
                "750000": 1e-01,
                "800000": 1e-01,
                "850000": 1e-01,
                "900000": 1e-01,
                "950000": 1e-01,
                "1000000": 1e-01
            },
            "hybrid-dcg": {
                "10000": 1e-01,
                "20000": 1e-01,
                "30000": 1e-01,
                "40000": 1e-01,
                "50000": 1e-01,
                "60000": 1e-01,
                "70000": 1e-01,
                "80000": 1e-01,
                "90000": 1e-01,
                "100000": 1e-01,
                "150000": 1e-01,
                "200000": 1e-01,
                "250000": 1e-01,
                "300000": 1e-01,
                "350000": 1e-01,
                "400000": 1e-01,
                "450000": 1e-01,
                "500000": 1e-01,
                "550000": 1e-01,
                "600000": 1e-01,
                "650000": 1e-01,
                "700000": 1e-01,
                "750000": 1e-01,
                "800000": 1e-01,
                "850000": 1e-01,
                "900000": 1e-01,
                "950000": 1e-01,
                "1000000": 1e-01
            },
            "hybrid-hinge": {
                "10000": 1e-01,
                "20000": 1e-01,
                "30000": 1e-01,
                "40000": 1e-01,
                "50000": 1e-01,
                "60000": 1e-01,
                "70000": 1e-01,
                "80000": 1e-01,
                "90000": 1e-01,
                "100000": 1e-01,
                "150000": 1e-01,
                "200000": 1e-01,
                "250000": 1e-01,
                "300000": 1e-01,
                "350000": 1e-01,
                "400000": 1e-01,
                "450000": 1e-01,
                "500000": 1e-01,
                "550000": 1e-01,
                "600000": 1e-01,
                "650000": 1e-01,
                "700000": 1e-01,
                "750000": 1e-01,
                "800000": 1e-01,
                "850000": 1e-01,
                "900000": 1e-01,
                "950000": 1e-01,
                "1000000": 1e-01
            }
        },
        "10": {
            "cf-dcg": {
                "10000": 1e-01,
                "20000": 1e-01,
                "30000": 1e-01,
                "40000": 1e-01,
                "50000": 1e-01,
                "60000": 1e-01,
                "70000": 1e-01,
                "80000": 1e-01,
                "90000": 1e-01,
                "100000": 1e-01,
                "150000": 1e-01,
                "200000": 1e-01,
                "250000": 1e-01,
                "300000": 1e-01,
                "350000": 1e-01,
                "400000": 1e-01,
                "450000": 1e-01,
                "500000": 1e-01,
                "550000": 1e-01,
                "600000": 1e-01,
                "650000": 1e-01,
                "700000": 1e-01,
                "750000": 1e-01,
                "800000": 1e-01,
                "850000": 1e-01,
                "900000": 1e-01,
                "950000": 1e-01,
                "1000000": 1e-01
            },
            "cf-hinge": {
                "10000": 1e-01,
                "20000": 1e-01,
                "30000": 1e-01,
                "40000": 1e-01,
                "50000": 1e-01,
                "60000": 1e-01,
                "70000": 1e-01,
                "80000": 1e-01,
                "90000": 1e-01,
                "100000": 1e-01,
                "150000": 1e-01,
                "200000": 1e-01,
                "250000": 1e-01,
                "300000": 1e-01,
                "350000": 1e-01,
                "400000": 1e-01,
                "450000": 1e-01,
                "500000": 1e-01,
                "550000": 1e-01,
                "600000": 1e-01,
                "650000": 1e-01,
                "700000": 1e-01,
                "750000": 1e-01,
                "800000": 1e-01,
                "850000": 1e-01,
                "900000": 1e-01,
                "950000": 1e-01,
                "1000000": 1e-01
            },
            "hybrid-dcg": {
                "10000": 1e-01,
                "20000": 1e-01,
                "30000": 1e-01,
                "40000": 1e-01,
                "50000": 1e-01,
                "60000": 1e-01,
                "70000": 1e-01,
                "80000": 1e-01,
                "90000": 1e-01,
                "100000": 1e-01,
                "150000": 1e-01,
                "200000": 1e-01,
                "250000": 1e-01,
                "300000": 1e-01,
                "350000": 1e-01,
                "400000": 1e-01,
                "450000": 1e-01,
                "500000": 1e-01,
                "550000": 1e-01,
                "600000": 1e-01,
                "650000": 1e-01,
                "700000": 1e-01,
                "750000": 1e-01,
                "800000": 1e-01,
                "850000": 1e-01,
                "900000": 1e-01,
                "950000": 1e-01,
                "1000000": 1e-01
            },
            "hybrid-hinge": {
                "10000": 1e-01,
                "20000": 1e-01,
                "30000": 1e-01,
                "40000": 1e-01,
                "50000": 1e-01,
                "60000": 1e-01,
                "70000": 1e-01,
                "80000": 1e-01,
                "90000": 1e-01,
                "100000": 1e-01,
                "150000": 1e-01,
                "200000": 1e-01,
                "250000": 1e-01,
                "300000": 1e-01,
                "350000": 1e-01,
                "400000": 1e-01,
                "450000": 1e-01,
                "500000": 1e-01,
                "550000": 1e-01,
                "600000": 1e-01,
                "650000": 1e-01,
                "700000": 1e-01,
                "750000": 1e-01,
                "800000": 1e-01,
                "850000": 1e-01,
                "900000": 1e-01,
                "950000": 1e-01,
                "1000000": 1e-01
            }
        }
    },
    "random[1.0]": {
        "0": {
            "cf-dcg": {
                "10000": 1e-01,
                "20000": 1e-01,
                "30000": 1e-01,
                "40000": 1e-01,
                "50000": 1e-01,
                "60000": 1e-01,
                "70000": 1e-01,
                "80000": 1e-01,
                "90000": 1e-01,
                "100000": 1e-01,
                "150000": 1e-01,
                "200000": 1e-01,
                "250000": 1e-01,
                "300000": 1e-01,
                "350000": 1e-01,
                "400000": 1e-01,
                "450000": 1e-01,
                "500000": 1e-01,
                "550000": 1e-01,
                "600000": 1e-01,
                "650000": 1e-01,
                "700000": 1e-01,
                "750000": 1e-01,
                "800000": 1e-01,
                "850000": 1e-01,
                "900000": 1e-01,
                "950000": 1e-01,
                "1000000": 1e-01
            },
            "cf-hinge": {
                "10000": 1e-01,
                "20000": 1e-01,
                "30000": 1e-01,
                "40000": 1e-01,
                "50000": 1e-01,
                "60000": 1e-01,
                "70000": 1e-01,
                "80000": 1e-01,
                "90000": 1e-01,
                "100000": 1e-01,
                "150000": 1e-01,
                "200000": 1e-01,
                "250000": 1e-01,
                "300000": 1e-01,
                "350000": 1e-01,
                "400000": 1e-01,
                "450000": 1e-01,
                "500000": 1e-01,
                "550000": 1e-01,
                "600000": 1e-01,
                "650000": 1e-01,
                "700000": 1e-01,
                "750000": 1e-01,
                "800000": 1e-01,
                "850000": 1e-01,
                "900000": 1e-01,
                "950000": 1e-01,
                "1000000": 1e-01
            },
            "hybrid-dcg": {
                "10000": 1e-01,
                "20000": 1e-01,
                "30000": 1e-01,
                "40000": 1e-01,
                "50000": 1e-01,
                "60000": 1e-01,
                "70000": 1e-01,
                "80000": 1e-01,
                "90000": 1e-01,
                "100000": 1e-01,
                "150000": 1e-01,
                "200000": 1e-01,
                "250000": 1e-01,
                "300000": 1e-01,
                "350000": 1e-01,
                "400000": 1e-01,
                "450000": 1e-01,
                "500000": 1e-01,
                "550000": 1e-01,
                "600000": 1e-01,
                "650000": 1e-01,
                "700000": 1e-01,
                "750000": 1e-01,
                "800000": 1e-01,
                "850000": 1e-01,
                "900000": 1e-01,
                "950000": 1e-01,
                "1000000": 1e-01
            },
            "hybrid-hinge": {
                "10000": 1e-01,
                "20000": 1e-01,
                "30000": 1e-01,
                "40000": 1e-01,
                "50000": 1e-01,
                "60000": 1e-01,
                "70000": 1e-01,
                "80000": 1e-01,
                "90000": 1e-01,
                "100000": 1e-01,
                "150000": 1e-01,
                "200000": 1e-01,
                "250000": 1e-01,
                "300000": 1e-01,
                "350000": 1e-01,
                "400000": 1e-01,
                "450000": 1e-01,
                "500000": 1e-01,
                "550000": 1e-01,
                "600000": 1e-01,
                "650000": 1e-01,
                "700000": 1e-01,
                "750000": 1e-01,
                "800000": 1e-01,
                "850000": 1e-01,
                "900000": 1e-01,
                "950000": 1e-01,
                "1000000": 1e-01
            }
        },
        "10": {
            "cf-dcg": {
                "10000": 1e-01,
                "20000": 1e-01,
                "30000": 1e-01,
                "40000": 1e-01,
                "50000": 1e-01,
                "60000": 1e-01,
                "70000": 1e-01,
                "80000": 1e-01,
                "90000": 1e-01,
                "100000": 1e-01,
                "150000": 1e-01,
                "200000": 1e-01,
                "250000": 1e-01,
                "300000": 1e-01,
                "350000": 1e-01,
                "400000": 1e-01,
                "450000": 1e-01,
                "500000": 1e-01,
                "550000": 1e-01,
                "600000": 1e-01,
                "650000": 1e-01,
                "700000": 1e-01,
                "750000": 1e-01,
                "800000": 1e-01,
                "850000": 1e-01,
                "900000": 1e-01,
                "950000": 1e-01,
                "1000000": 1e-01
            },
            "cf-hinge": {
                "10000": 1e-01,
                "20000": 1e-01,
                "30000": 1e-01,
                "40000": 1e-01,
                "50000": 1e-01,
                "60000": 1e-01,
                "70000": 1e-01,
                "80000": 1e-01,
                "90000": 1e-01,
                "100000": 1e-01,
                "150000": 1e-01,
                "200000": 1e-01,
                "250000": 1e-01,
                "300000": 1e-01,
                "350000": 1e-01,
                "400000": 1e-01,
                "450000": 1e-01,
                "500000": 1e-01,
                "550000": 1e-01,
                "600000": 1e-01,
                "650000": 1e-01,
                "700000": 1e-01,
                "750000": 1e-01,
                "800000": 1e-01,
                "850000": 1e-01,
                "900000": 1e-01,
                "950000": 1e-01,
                "1000000": 1e-01
            },
            "hybrid-dcg": {
                "10000": 1e-01,
                "20000": 1e-01,
                "30000": 1e-01,
                "40000": 1e-01,
                "50000": 1e-01,
                "60000": 1e-01,
                "70000": 1e-01,
                "80000": 1e-01,
                "90000": 1e-01,
                "100000": 1e-01,
                "150000": 1e-01,
                "200000": 1e-01,
                "250000": 1e-01,
                "300000": 1e-01,
                "350000": 1e-01,
                "400000": 1e-01,
                "450000": 1e-01,
                "500000": 1e-01,
                "550000": 1e-01,
                "600000": 1e-01,
                "650000": 1e-01,
                "700000": 1e-01,
                "750000": 1e-01,
                "800000": 1e-01,
                "850000": 1e-01,
                "900000": 1e-01,
                "950000": 1e-01,
                "1000000": 1e-01
            },
            "hybrid-hinge": {
                "10000": 1e-01,
                "20000": 1e-01,
                "30000": 1e-01,
                "40000": 1e-01,
                "50000": 1e-01,
                "60000": 1e-01,
                "70000": 1e-01,
                "80000": 1e-01,
                "90000": 1e-01,
                "100000": 1e-01,
                "150000": 1e-01,
                "200000": 1e-01,
                "250000": 1e-01,
                "300000": 1e-01,
                "350000": 1e-01,
                "400000": 1e-01,
                "450000": 1e-01,
                "500000": 1e-01,
                "550000": 1e-01,
                "600000": 1e-01,
                "650000": 1e-01,
                "700000": 1e-01,
                "750000": 1e-01,
                "800000": 1e-01,
                "850000": 1e-01,
                "900000": 1e-01,
                "950000": 1e-01,
                "1000000": 1e-01
            }
        }
    },
    "random[2.0]": {
        "0": {
            "cf-dcg": {
                "10000": 1e-01,
                "20000": 1e-01,
                "30000": 1e-01,
                "40000": 1e-01,
                "50000": 1e-01,
                "60000": 1e-01,
                "70000": 1e-01,
                "80000": 1e-01,
                "90000": 1e-01,
                "100000": 1e-01,
                "150000": 1e-01,
                "200000": 1e-01,
                "250000": 1e-01,
                "300000": 1e-01,
                "350000": 1e-01,
                "400000": 1e-01,
                "450000": 1e-01,
                "500000": 1e-01,
                "550000": 1e-01,
                "600000": 1e-01,
                "650000": 1e-01,
                "700000": 1e-01,
                "750000": 1e-01,
                "800000": 1e-01,
                "850000": 1e-01,
                "900000": 1e-01,
                "950000": 1e-01,
                "1000000": 1e-01
            },
            "cf-hinge": {
                "10000": 1e-01,
                "20000": 1e-01,
                "30000": 1e-01,
                "40000": 1e-01,
                "50000": 1e-01,
                "60000": 1e-01,
                "70000": 1e-01,
                "80000": 1e-01,
                "90000": 1e-01,
                "100000": 1e-01,
                "150000": 1e-01,
                "200000": 1e-01,
                "250000": 1e-01,
                "300000": 1e-01,
                "350000": 1e-01,
                "400000": 1e-01,
                "450000": 1e-01,
                "500000": 1e-01,
                "550000": 1e-01,
                "600000": 1e-01,
                "650000": 1e-01,
                "700000": 1e-01,
                "750000": 1e-01,
                "800000": 1e-01,
                "850000": 1e-01,
                "900000": 1e-01,
                "950000": 1e-01,
                "1000000": 1e-01
            },
            "hybrid-dcg": {
                "10000": 1e-01,
                "20000": 1e-01,
                "30000": 1e-01,
                "40000": 1e-01,
                "50000": 1e-01,
                "60000": 1e-01,
                "70000": 1e-01,
                "80000": 1e-01,
                "90000": 1e-01,
                "100000": 1e-01,
                "150000": 1e-01,
                "200000": 1e-01,
                "250000": 1e-01,
                "300000": 1e-01,
                "350000": 1e-01,
                "400000": 1e-01,
                "450000": 1e-01,
                "500000": 1e-01,
                "550000": 1e-01,
                "600000": 1e-01,
                "650000": 1e-01,
                "700000": 1e-01,
                "750000": 1e-01,
                "800000": 1e-01,
                "850000": 1e-01,
                "900000": 1e-01,
                "950000": 1e-01,
                "1000000": 1e-01
            },
            "hybrid-hinge": {
                "10000": 1e-01,
                "20000": 1e-01,
                "30000": 1e-01,
                "40000": 1e-01,
                "50000": 1e-01,
                "60000": 1e-01,
                "70000": 1e-01,
                "80000": 1e-01,
                "90000": 1e-01,
                "100000": 1e-01,
                "150000": 1e-01,
                "200000": 1e-01,
                "250000": 1e-01,
                "300000": 1e-01,
                "350000": 1e-01,
                "400000": 1e-01,
                "450000": 1e-01,
                "500000": 1e-01,
                "550000": 1e-01,
                "600000": 1e-01,
                "650000": 1e-01,
                "700000": 1e-01,
                "750000": 1e-01,
                "800000": 1e-01,
                "850000": 1e-01,
                "900000": 1e-01,
                "950000": 1e-01,
                "1000000": 1e-01
            }
        },
        "10": {
            "cf-dcg": {
                "10000": 1e-01,
                "20000": 1e-01,
                "30000": 1e-01,
                "40000": 1e-01,
                "50000": 1e-01,
                "60000": 1e-01,
                "70000": 1e-01,
                "80000": 1e-01,
                "90000": 1e-01,
                "100000": 1e-01,
                "150000": 1e-01,
                "200000": 1e-01,
                "250000": 1e-01,
                "300000": 1e-01,
                "350000": 1e-01,
                "400000": 1e-01,
                "450000": 1e-01,
                "500000": 1e-01,
                "550000": 1e-01,
                "600000": 1e-01,
                "650000": 1e-01,
                "700000": 1e-01,
                "750000": 1e-01,
                "800000": 1e-01,
                "850000": 1e-01,
                "900000": 1e-01,
                "950000": 1e-01,
                "1000000": 1e-01
            },
            "cf-hinge": {
                "10000": 1e-01,
                "20000": 1e-01,
                "30000": 1e-01,
                "40000": 1e-01,
                "50000": 1e-01,
                "60000": 1e-01,
                "70000": 1e-01,
                "80000": 1e-01,
                "90000": 1e-01,
                "100000": 1e-01,
                "150000": 1e-01,
                "200000": 1e-01,
                "250000": 1e-01,
                "300000": 1e-01,
                "350000": 1e-01,
                "400000": 1e-01,
                "450000": 1e-01,
                "500000": 1e-01,
                "550000": 1e-01,
                "600000": 1e-01,
                "650000": 1e-01,
                "700000": 1e-01,
                "750000": 1e-01,
                "800000": 1e-01,
                "850000": 1e-01,
                "900000": 1e-01,
                "950000": 1e-01,
                "1000000": 1e-01
            },
            "hybrid-dcg": {
                "10000": 1e-01,
                "20000": 1e-01,
                "30000": 1e-01,
                "40000": 1e-01,
                "50000": 1e-01,
                "60000": 1e-01,
                "70000": 1e-01,
                "80000": 1e-01,
                "90000": 1e-01,
                "100000": 1e-01,
                "150000": 1e-01,
                "200000": 1e-01,
                "250000": 1e-01,
                "300000": 1e-01,
                "350000": 1e-01,
                "400000": 1e-01,
                "450000": 1e-01,
                "500000": 1e-01,
                "550000": 1e-01,
                "600000": 1e-01,
                "650000": 1e-01,
                "700000": 1e-01,
                "750000": 1e-01,
                "800000": 1e-01,
                "850000": 1e-01,
                "900000": 1e-01,
                "950000": 1e-01,
                "1000000": 1e-01
            },
            "hybrid-hinge": {
                "10000": 1e-01,
                "20000": 1e-01,
                "30000": 1e-01,
                "40000": 1e-01,
                "50000": 1e-01,
                "60000": 1e-01,
                "70000": 1e-01,
                "80000": 1e-01,
                "90000": 1e-01,
                "100000": 1e-01,
                "150000": 1e-01,
                "200000": 1e-01,
                "250000": 1e-01,
                "300000": 1e-01,
                "350000": 1e-01,
                "400000": 1e-01,
                "450000": 1e-01,
                "500000": 1e-01,
                "550000": 1e-01,
                "600000": 1e-01,
                "650000": 1e-01,
                "700000": 1e-01,
                "750000": 1e-01,
                "800000": 1e-01,
                "850000": 1e-01,
                "900000": 1e-01,
                "950000": 1e-01,
                "1000000": 1e-01
            }
        }
    }
}